darca_llm/__init__.py
darca_llm/__version__.py
darca_llm/llm.py
darca_llm-0.2.0.dist-info/LICENSE
darca_llm-0.2.0.dist-info/METADATA
darca_llm-0.2.0.dist-info/WHEEL
darca_llm-0.2.0.dist-info/RECORD
